fastapi_activitypub/__init__.py
fastapi_activitypub-0.1.0.dist-info/LICENSE
fastapi_activitypub-0.1.0.dist-info/METADATA
fastapi_activitypub-0.1.0.dist-info/WHEEL
fastapi_activitypub-0.1.0.dist-info/RECORD
