Metadata-Version: 2.1
Name: fastapi-activitypub
Version: 0.1.0
Summary: Ultraminimal Activitypub SDK for FastAPI
Home-page: https://github.com/p2p-ld/fastapi-activitypub
License: AGPL-3.0
Author: sneakers-the-rat
Author-email: sneakers-the-rat@protonmail.com
Requires-Python: >=3.11,<4.0
Classifier: License :: OSI Approved :: GNU Affero General Public License v3
Classifier: Programming Language :: Python :: 3
Classifier: Programming Language :: Python :: 3.11
Requires-Dist: fastapi (>=0.108.0)
Requires-Dist: pydantic (>=2.5.3,<3.0.0)
Project-URL: Repository, https://github.com/p2p-ld/fastapi-activitypub
